ezoutlet/__init__.py
ezoutlet/cli.py
ezoutlet/constants.py
ezoutlet/core.py
ezoutlet/entrypoint.py
ezoutlet/logging.py
ezoutlet/responses.py
ezoutlet/utils.py
ezoutlet_sdk-0.1.0.dist-info/AUTHORS.md
ezoutlet_sdk-0.1.0.dist-info/LICENSE
ezoutlet_sdk-0.1.0.dist-info/METADATA
ezoutlet_sdk-0.1.0.dist-info/WHEEL
ezoutlet_sdk-0.1.0.dist-info/entry_points.txt
ezoutlet_sdk-0.1.0.dist-info/top_level.txt
ezoutlet_sdk-0.1.0.dist-info/RECORD
