Metadata-Version: 2.1
Name: ezoutlet-sdk
Version: 0.1.0
Summary: API and command line tools to interface with EZOutlets.
Author-email: Tim Santor <tsantor@xstudios.com>
Project-URL: Repository, https://github.com/tsantor/ezoutlet-sdk.git
Project-URL: Issues, https://github.com/tsantor/ezoutlet-sdk/issues
Project-URL: Changelog, https://github.com/tsantor/ezoutlet-sdk/blob/master/HISTORY.md
Classifier: Development Status :: 5 - Production/Stable
Classifier: Environment :: Console
Classifier: Intended Audience :: Developers
Classifier: Natural Language :: English
Classifier: Programming Language :: Python :: 3.8
Classifier: Programming Language :: Python :: 3.9
Classifier: Programming Language :: Python :: 3.10
Classifier: Programming Language :: Python :: 3.11
Classifier: Programming Language :: Python :: 3.12
Requires-Python: >=3.8
License-File: LICENSE
License-File: AUTHORS.md
Requires-Dist: click
Requires-Dist: rich
Requires-Dist: requests
Requires-Dist: defusedxml
Provides-Extra: dev
